comfyui_api_client/__init__.py
comfyui_api_client/api_helpers.py
comfyui_api_client/open_websocket.py
comfyui_api_client/text2image.py
comfyui_api_client/websocket_api.py
tests/__init__.py
comfyui_api_client-0.1.0.dist-info/METADATA
comfyui_api_client-0.1.0.dist-info/WHEEL
comfyui_api_client-0.1.0.dist-info/top_level.txt
comfyui_api_client-0.1.0.dist-info/RECORD
