Metadata-Version: 2.1
Name: comfyui-api-client
Version: 0.1.0
Summary: A Python API client for ComfyUI to generate images through WebSocket and HTTP requests.
Home-page: https://github.com/yourusername/comfyui-api-client
Author: Kazancev Danil
Author-email: your.email@example.com
License: MIT
Classifier: Programming Language :: Python :: 3
Classifier: License :: OSI Approved :: MIT License
Classifier: Operating System :: OS Independent
Requires-Python: >=3.7
Requires-Dist: Pillow==10.2.0
Requires-Dist: websocket-client==1.7.0
Requires-Dist: requests_toolbelt==1.0.0
